tudo/__init__.py
tudo/app.py
tudo/controller.py
tudo/store.py
tudo/task.py
tudo-0.1.0.dev6.dist-info/DESCRIPTION.rst
tudo-0.1.0.dev6.dist-info/METADATA
tudo-0.1.0.dev6.dist-info/RECORD
tudo-0.1.0.dev6.dist-info/WHEEL
tudo-0.1.0.dev6.dist-info/entry_points.txt
tudo-0.1.0.dev6.dist-info/metadata.json
tudo-0.1.0.dev6.dist-info/top_level.txt
