Metadata-Version: 2.0
Name: tudo
Version: 0.1.0.dev6
Summary: A simple command-line based TODO-app in Python
Home-page: https://github.com/Sukram21/TUDO
Author: Markus Müller, Martin Zehendner
Author-email: mail@muellermarkus.com
License: MIT
Keywords: todo organization command-line
Platform: UNKNOWN
Classifier: Development Status :: 3 - Alpha
Classifier: Intended Audience :: Developers
Classifier: Topic :: Office/Business :: Scheduling
Classifier: License :: OSI Approved :: MIT License
Classifier: Programming Language :: Python :: 3
Requires-Dist: pytz
Requires-Dist: tabulate
